{
  "_fv": 57,
  "_type": "tool",
  "definition": {
    "toolType": "Sword",
    "renderType": 1,
    "blockingRenderType": 0,
    "texture": "frost_sword",
    "customModelName": "frost_sword:default",
    "blockingModelName": "Normal blocking",
    "name": "Frost Blade (model wip)",
    "specialInformation": {
      "fixedValue": []
    },
    "creativeTab": {
      "value": "CUSTOM:SoloLevelingWeapons"
    },
    "harvestLevel": 1,
    "efficiency": 4.0,
    "attackSpeed": 1.6,
    "enchantability": 2,
    "damageVsEntity": 10.0,
    "usageCount": 0,
    "blocksAffected": [],
    "glowCondition": {
      "fixedValue": false,
      "name": "DemonKingsLongSwordHasItemGlowingEffect"
    },
    "repairItems": [],
    "immuneToFire": false,
    "stayInGridWhenCrafting": false,
    "damageOnCrafting": false,
    "onEntityHitWith": {
      "name": "FrostBladeLivingEntityIsHitWithTool"
    }
  }
}