{
  "_fv": 57,
  "_type": "animatedentity",
  "definition": {
    "mobName": "Goblin Club",
    "mobLabel": "",
    "mobModelTexture": "goblin_club_shadow.png",
    "mobModelGlowTexture": "",
    "visualScale": {
      "fixedValue": 1.0
    },
    "boundingBoxScale": {
      "fixedValue": 1.0
    },
    "entityDataEntries": [
      {
        "name": "state",
        "type": "string",
        "value": "idle"
      },
      {
        "min": -2147483648,
        "max": 2147483647,
        "name": "MF",
        "type": "integer",
        "value": 0
      }
    ],
    "modelWidth": 0.6,
    "modelHeight": 1.8,
    "modelShadowSize": 0.5,
    "mountedYOffset": 0.0,
    "hasSpawnEgg": false,
    "spawnEggBaseColor": {
      "value": -16751104,
      "falpha": 0.0
    },
    "spawnEggDotColor": {
      "value": -9425152,
      "falpha": 0.0
    },
    "creativeTab": {
      "value": "MISC"
    },
    "isBoss": false,
    "bossBarColor": "PINK",
    "bossBarType": "PROGRESS",
    "equipmentMainHand": {
      "value": ""
    },
    "equipmentOffHand": {
      "value": ""
    },
    "equipmentHelmet": {
      "value": ""
    },
    "equipmentBody": {
      "value": ""
    },
    "equipmentLeggings": {
      "value": ""
    },
    "equipmentBoots": {
      "value": ""
    },
    "mobBehaviourType": "Mob",
    "mobCreatureType": "UNDEFINED",
    "attackStrength": 0,
    "attackKnockback": 0.0,
    "knockbackResistance": 0.0,
    "movementSpeed": 0.225,
    "armorBaseValue": 5.0,
    "trackingRange": 64,
    "followRange": 16,
    "health": 12,
    "xpAmount": 0,
    "waterMob": false,
    "flyingMob": false,
    "guiBoundTo": "<NONE>",
    "inventorySize": 9,
    "inventoryStackSize": 64,
    "deathTime": 40,
    "lerp": 4,
    "disableCollisions": false,
    "ridable": false,
    "canControlForward": false,
    "canControlStrafe": false,
    "immuneToFire": false,
    "immuneToArrows": false,
    "immuneToFallDamage": false,
    "immuneToCactus": false,
    "immuneToDrowning": false,
    "immuneToLightning": false,
    "immuneToPotions": false,
    "immuneToPlayer": false,
    "immuneToExplosion": false,
    "immuneToTrident": false,
    "immuneToAnvil": false,
    "immuneToWither": false,
    "immuneToDragonBreath": false,
    "mobDrop": {
      "value": ""
    },
    "livingSound": {
      "value": ""
    },
    "hurtSound": {
      "value": "entity.generic.hurt"
    },
    "deathSound": {
      "value": "entity.generic.death"
    },
    "stepSound": {
      "value": ""
    },
    "onMobTickUpdate": {
      "name": "GoblinClubShadowOnEntityTickUpdate"
    },
    "hasAI": true,
    "aiBase": "(none)",
    "aixml": "<xml xmlns=\"https://developers.google.com/blockly/xml\"><block type=\"aitasks_container\" deletable=\"false\" x=\"40\" y=\"40\"><next><block type=\"attack_action\"><field name=\"callhelp\">FALSE</field><field name=\"condition\">null,null</field><next><block type=\"attack_entity\"><field name=\"insight\">FALSE</field><field name=\"nearby\">FALSE</field><field name=\"entity\">CUSTOM:GoblinClub</field><field name=\"condition\">IsBerserk,IsBerserk</field><next><block type=\"attack_entity\"><field name=\"insight\">FALSE</field><field name=\"nearby\">FALSE</field><field name=\"entity\">CUSTOM:GoblinArcher</field><field name=\"condition\">IsBerserk,IsBerserk</field><next><block type=\"attack_entity\"><field name=\"insight\">FALSE</field><field name=\"nearby\">FALSE</field><field name=\"entity\">CUSTOM:GoblinMage</field><field name=\"condition\">IsBerserk,IsBerserk</field><next><block type=\"attack_entity\"><field name=\"insight\">FALSE</field><field name=\"nearby\">FALSE</field><field name=\"entity\">CUSTOM:GoblinKing</field><field name=\"condition\">IsBerserk,IsBerserk</field><next><block type=\"attack_entity\"><field name=\"insight\">FALSE</field><field name=\"nearby\">FALSE</field><field name=\"entity\">CUSTOM:DKnight1</field><field name=\"condition\">IsBerserk,IsBerserk</field><next><block type=\"attack_entity\"><field name=\"insight\">FALSE</field><field name=\"nearby\">FALSE</field><field name=\"entity\">CUSTOM:DKnight2</field><field name=\"condition\">IsBerserk,IsBerserk</field><next><block type=\"attack_entity\"><field name=\"insight\">FALSE</field><field name=\"nearby\">FALSE</field><field name=\"entity\">CUSTOM:DKnight3</field><field name=\"condition\">IsBerserk,IsBerserk</field><next><block type=\"attack_entity\"><field name=\"insight\">FALSE</field><field name=\"nearby\">FALSE</field><field name=\"entity\">CUSTOM:Orc</field><field name=\"condition\">IsBerserk,IsBerserk</field><next><block type=\"attack_entity\"><field name=\"insight\">FALSE</field><field name=\"nearby\">FALSE</field><field name=\"entity\">CUSTOM:Kasaka</field><field name=\"condition\">IsBerserk,IsBerserk</field><next><block type=\"attack_entity\"><field name=\"insight\">FALSE</field><field name=\"nearby\">FALSE</field><field name=\"entity\">CUSTOM:MiniGemGolem</field><field name=\"condition\">IsBerserk,IsBerserk</field><next><block type=\"attack_entity\"><field name=\"insight\">FALSE</field><field name=\"nearby\">FALSE</field><field name=\"entity\">CUSTOM:GemGolem</field><field name=\"condition\">IsBerserk,IsBerserk</field><next><block type=\"attack_entity\"><field name=\"insight\">FALSE</field><field name=\"nearby\">FALSE</field><field name=\"entity\">CUSTOM:BeruBoss</field><field name=\"condition\">IsBerserk,IsBerserk</field><next><block type=\"attack_entity\"><field name=\"insight\">FALSE</field><field name=\"nearby\">FALSE</field><field name=\"entity\">CUSTOM:BloodRedComIgris</field><field name=\"condition\">IsBerserk,IsBerserk</field><next><block type=\"attack_entity\"><field name=\"insight\">FALSE</field><field name=\"nearby\">FALSE</field><field name=\"entity\">CUSTOM:AncientSamurai</field><field name=\"condition\">IsBerserk,IsBerserk</field><next><block type=\"attack_entity\"><field name=\"insight\">FALSE</field><field name=\"nearby\">FALSE</field><field name=\"entity\">CUSTOM:AncientGolem</field><field name=\"condition\">IsBerserk,IsBerserk</field><next><block type=\"attack_entity\"><field name=\"insight\">FALSE</field><field name=\"nearby\">FALSE</field><field name=\"entity\">CUSTOM:Centipede</field><field name=\"condition\">IsBerserk,IsBerserk</field><next><block type=\"attack_entity\"><field name=\"insight\">FALSE</field><field name=\"nearby\">FALSE</field><field name=\"entity\">CUSTOM:Kamish</field><field name=\"condition\">IsBerserk,IsBerserk</field><next><block type=\"attack_entity\"><field name=\"insight\">FALSE</field><field name=\"nearby\">FALSE</field><field name=\"entity\">CUSTOM:StoneGolem</field><field name=\"condition\">IsBerserk,IsBerserk</field><next><block type=\"attack_entity\"><field name=\"insight\">FALSE</field><field name=\"nearby\">FALSE</field><field name=\"entity\">EntityMob</field><field name=\"condition\">IsBerserk,IsBerserk</field><next><block type=\"fight_as_owner\"><field name=\"condition\">null,null</field><next><block type=\"follow_parent\"><field name=\"speed\">1.6</field><field name=\"condition\">null,null</field><next><block type=\"wander\"><field name=\"speed\">0.5</field><field name=\"condition\">null,null</field><next><block type=\"protect_owner\"><field name=\"condition\">null,null</field><next><block type=\"look_around\"><field name=\"condition\">null,null</field><next><block type=\"swim_in_water\"><field name=\"condition\">null,null</field><next><block type=\"doors_open\"><field name=\"condition\">null,null</field></block></next></block></next></block></next></block></next></block></next></block></next></block></next></block></next></block></next></block></next></block></next></block></next></block></next></block></next></block></next></block></next></block></next></block></next></block></next></block></next></block></next></block></next></block></next></block></next></block></next></block></next></block></next></block></xml>",
    "model": "goblin_club.geo.json",
    "groupName": "h_head",
    "animation1": "idle",
    "animation2": "walk",
    "animation3": "death",
    "animation4": "",
    "animation5": "",
    "animation6": "",
    "animation7": "",
    "animation8": "",
    "animation9": "",
    "animation10": "",
    "enable2": true,
    "enable3": true,
    "enable4": false,
    "enable5": false,
    "enable6": false,
    "enable7": false,
    "enable8": false,
    "enable9": false,
    "enable10": false,
    "breedable": true,
    "tameable": true,
    "disableDeathRotation": true,
    "headMovement": true,
    "eyeHeight": false,
    "breedTriggerItems": [],
    "ranged": false,
    "rangedAttackItem": {
      "value": ""
    },
    "rangedItemType": "Default item",
    "rangedAttackInterval": 20,
    "rangedAttackRadius": 10.0,
    "height": 1.0,
    "spawnThisMob": false,
    "doesDespawnWhenIdle": false,
    "spawningProbability": 20,
    "mobSpawningType": "monster",
    "minNumberOfMobsPerGroup": 4,
    "maxNumberOfMobsPerGroup": 4,
    "restrictionBiomes": [],
    "spawnInDungeons": false
  }
}