{
  "_fv": 57,
  "_type": "gui",
  "definition": {
    "type": 0,
    "width": 0,
    "height": 0,
    "inventoryOffsetX": 0,
    "inventoryOffsetY": 0,
    "renderBgLayer": true,
    "doesPauseGame": false,
    "components": [
      {
        "type": "image",
        "data": {
          "image": "basewide2.png",
          "use1Xscale": true,
          "x": 63,
          "y": 1
        }
      },
      {
        "type": "entitymodel",
        "data": {
          "entityModel": {
            "name": "ReturnShadowIgris"
          },
          "displayCondition": {
            "name": "IgrisSpawned"
          },
          "scale": 30,
          "rotationX": 0,
          "followMouseMovement": true,
          "x": 101,
          "y": 103
        }
      },
      {
        "type": "entitymodel",
        "data": {
          "entityModel": {
            "name": "ReturnShadowBeru"
          },
          "displayCondition": {
            "name": "BeruSpawned"
          },
          "scale": 30,
          "rotationX": 0,
          "followMouseMovement": false,
          "x": 305,
          "y": 101
        }
      },
      {
        "type": "image",
        "data": {
          "image": "shadowunlocked.png",
          "use1Xscale": true,
          "displayCondition": {
            "name": "IgrisNotSpawned"
          },
          "x": 79,
          "y": 22
        }
      },
      {
        "type": "label",
        "data": {
          "name": "label_not_spawned",
          "text": {
            "fixedValue": "Igris"
          },
          "color": {
            "value": -10092544,
            "falpha": 0.0
          },
          "displayCondition": {
            "name": "IgrisNotSpawned"
          },
          "x": 99,
          "y": 67
        }
      },
      {
        "type": "image",
        "data": {
          "image": "shadowunlocked.png",
          "use1Xscale": true,
          "x": 281,
          "y": 20
        }
      },
      {
        "type": "label",
        "data": {
          "name": "label_available_orders",
          "text": {
            "fixedValue": "Available Orders"
          },
          "color": {
            "value": -16777216,
            "falpha": 0.0
          },
          "x": 168,
          "y": 26
        }
      },
      {
        "type": "button",
        "data": {
          "name": "button_berserk",
          "text": "Go Berserk",
          "isUndecorated": false,
          "onClick": {
            "name": "BerserkOwnerButton"
          },
          "width": 61,
          "height": 20,
          "x": 177,
          "y": 46
        }
      },
      {
        "type": "label",
        "data": {
          "name": "label_beru",
          "text": {
            "fixedValue": "Beru"
          },
          "color": {
            "value": -10092544,
            "falpha": 0.0
          },
          "x": 304,
          "y": 65
        }
      },
      {
        "type": "label",
        "data": {
          "name": "label_proc_return_shadow_sold",
          "text": {
            "fixedValue": "",
            "name": "ReturnShadowSold"
          },
          "color": {
            "value": -16777216,
            "falpha": 0.0
          },
          "x": 177,
          "y": 127
        }
      },
      {
        "type": "label",
        "data": {
          "name": "label_proc_return_shadow_gob",
          "text": {
            "fixedValue": "",
            "name": "ReturnShadowGob"
          },
          "color": {
            "value": -16777216,
            "falpha": 0.0
          },
          "x": 193,
          "y": 146
        }
      },
      {
        "type": "label",
        "data": {
          "name": "label_proc_return_shadow_wolf",
          "text": {
            "fixedValue": "",
            "name": "ReturnShadowWolf"
          },
          "color": {
            "value": -16777216,
            "falpha": 0.0
          },
          "x": 151,
          "y": 202
        }
      },
      {
        "type": "label",
        "data": {
          "name": "label_shadow_storage",
          "text": {
            "fixedValue": "Shadow Storage"
          },
          "color": {
            "value": -16777216,
            "falpha": 0.0
          },
          "x": 287,
          "y": 138
        }
      },
      {
        "type": "label",
        "data": {
          "name": "label_proc_return_shadow_storage_level",
          "text": {
            "fixedValue": "",
            "name": "ReturnShadowStorageLevel"
          },
          "color": {
            "value": -16777216,
            "falpha": 0.0
          },
          "x": 285,
          "y": 152
        }
      },
      {
        "type": "button",
        "data": {
          "name": "button_dismiss_soldiers",
          "text": "Dismiss Soldiers",
          "isUndecorated": false,
          "onClick": {
            "name": "DismissSoldier"
          },
          "width": 108,
          "height": 20,
          "x": 68,
          "y": 122
        }
      },
      {
        "type": "button",
        "data": {
          "name": "button_dismiss_goblin_club",
          "text": "Dismiss Goblin Club",
          "isUndecorated": false,
          "onClick": {
            "name": "DismissGoblin"
          },
          "width": 124,
          "height": 20,
          "x": 68,
          "y": 141
        }
      },
      {
        "type": "button",
        "data": {
          "name": "button_dismiss_goblin_mage",
          "text": "Dismiss Goblin Mage",
          "isUndecorated": false,
          "onClick": {
            "name": "DismissGoblinMage"
          },
          "width": 124,
          "height": 20,
          "x": 68,
          "y": 179
        }
      },
      {
        "type": "button",
        "data": {
          "name": "button_dismisswolf",
          "text": "Dismiss Wolf",
          "isUndecorated": false,
          "onClick": {
            "name": "DismissWolf"
          },
          "width": 82,
          "height": 20,
          "x": 68,
          "y": 197
        }
      },
      {
        "type": "button",
        "data": {
          "name": "button_dismiss_goblin_club1",
          "text": "Dismiss Goblin Archer",
          "isUndecorated": false,
          "onClick": {
            "name": "DismissGoblinArcher"
          },
          "width": 124,
          "height": 20,
          "x": 68,
          "y": 160
        }
      },
      {
        "type": "label",
        "data": {
          "name": "label_proc_return_goblin_archer",
          "text": {
            "fixedValue": "",
            "name": "ReturnGoblinArcher"
          },
          "color": {
            "value": -16777216,
            "falpha": 0.0
          },
          "x": 193,
          "y": 164
        }
      },
      {
        "type": "label",
        "data": {
          "name": "label_proc_return_shadow_gob_mage",
          "text": {
            "fixedValue": "",
            "name": "ReturnShadowGobMage"
          },
          "color": {
            "value": -16777216,
            "falpha": 0.0
          },
          "x": 193,
          "y": 184
        }
      }
    ],
    "gridSettings": {
      "sx": 18,
      "sy": 18,
      "ox": 11,
      "oy": 15,
      "snapOnGrid": false
    }
  }
}